[
  { "word": "pollution", "vietnamese": "ô nhiễm", "example": "Air pollution is a serious problem in many cities." },
  { "word": "climate change", "vietnamese": "biến đổi khí hậu", "example": "Climate change affects the whole world." },
  { "word": "deforestation", "vietnamese": "phá rừng", "example": "Deforestation destroys animal habitats." },
  { "word": "recycling", "vietnamese": "tái chế", "example": "Recycling helps reduce the amount of waste." },
  { "word": "global warming", "vietnamese": "nóng lên toàn cầu", "example": "Global warming causes ice to melt at the poles." },
  { "word": "natural resources", "vietnamese": "tài nguyên thiên nhiên", "example": "We should use natural resources wisely." }
]
